scedar/__init__.py
scedar/utils.py
scedar/cluster/__init__.py
scedar/cluster/community.py
scedar/cluster/community_mirac.py
scedar/cluster/mirac.py
scedar/eda/__init__.py
scedar/eda/mdl.py
scedar/eda/mtype.py
scedar/eda/plot.py
scedar/eda/sdm.py
scedar/eda/sfm.py
scedar/eda/slcs.py
scedar/eda/stats.py
scedar/knn/__init__.py
scedar/knn/detection.py
scedar/knn/imputation.py
scedar-0.2.0.dist-info/LICENSE.txt
scedar-0.2.0.dist-info/METADATA
scedar-0.2.0.dist-info/WHEEL
scedar-0.2.0.dist-info/top_level.txt
scedar-0.2.0.dist-info/RECORD
