Metadata-Version: 2.1
Name: scedar
Version: 0.2.0
Summary: Single-cell exploratory data analysis for RNA-Seq
Home-page: http://github.com/logstar/scedar
Author: Yuanchao Zhang
Author-email: logstarx@gmail.com
License: MIT
Platform: UNKNOWN
Classifier: Development Status :: 3 - Alpha
Classifier: Programming Language :: Python :: 3.5
Classifier: Programming Language :: Python :: 3.6
Classifier: Programming Language :: Python :: 3.7
Requires-Python: >=3.5, <3.8
Requires-Dist: numpy
Requires-Dist: scipy
Requires-Dist: matplotlib (<=3.1.0)
Requires-Dist: pandas
Requires-Dist: seaborn (<=0.9.0)
Requires-Dist: scikit-learn (<=0.21)
Requires-Dist: xgboost
Requires-Dist: networkx
Requires-Dist: fa2
Requires-Dist: umap-learn
Requires-Dist: python-igraph
Requires-Dist: nmslib
Requires-Dist: leidenalg
